[{"ID":"4A","name":"iWiRHiH_iWNFbFf"},{"ID":"4B","name":"iWULXf_a_iWOJB"},{"ID":"4D","name":"iWCYiLB"},{"ID":"4E","name":"iWiRHiH_iWRMJbf"},{"ID":"4F","name":"iWiRHiH_iWVLJbf"},{"ID":"4G","name":"aFHiC_iWUbL"},{"ID":"4H","name":"iWHihJf"},{"ID":"4I","name":"iWXDWD"},{"ID":"4J","name":"iWBbR_aiWMJij"},{"ID":"4K","name":"UbL_iWXLiFf"},{"ID":"4L","name":"UbL_iWKXY_a_iWLJRf"},{"ID":"4M","name":"iWMBVf"},{"ID":"4N","name":"iWXLCUbXiC"},{"ID":"4P","name":"iWKaibi"},{"ID":"4Q","name":"JLX_iWiMViW"},{"ID":"4R","name":"UbL_iWXFbP"},{"ID":"4T","name":"iWXVRB_a_XCaiKb_iWXLCPbWiC"},{"ID":"4U","name":"iWLWX"},{"ID":"4V","name":"UiBWbf_iWULXf"},{"ID":"4X","name":"MBZ__XYFJT"},{"ID":"4Z","name":"iWUiLX_XMCJV_iWiNSJ"}]